newyorkfed_pandas/__init__.py
newyorkfed_pandas/rrp.py
newyorkfed_pandas-0.0.2.dist-info/METADATA
newyorkfed_pandas-0.0.2.dist-info/WHEEL
newyorkfed_pandas-0.0.2.dist-info/licenses/LICENSE
newyorkfed_pandas-0.0.2.dist-info/RECORD
